napari_yolo5_mitosis_detector/__init__.py
napari_yolo5_mitosis_detector/_reader.py
napari_yolo5_mitosis_detector/_sample_data.py
napari_yolo5_mitosis_detector/_widget.py
napari_yolo5_mitosis_detector/_writer.py
napari_yolo5_mitosis_detector/core.py
napari_yolo5_mitosis_detector/napari.yaml
napari_yolo5_mitosis_detector/post_process.py
napari_yolo5_mitosis_detector/_tests/__init__.py
napari_yolo5_mitosis_detector/_tests/test_core.py
napari_yolo5_mitosis_detector/_tests/test_reader.py
napari_yolo5_mitosis_detector/_tests/test_sample_data.py
napari_yolo5_mitosis_detector/_tests/test_widget.py
napari_yolo5_mitosis_detector/_tests/test_writer.py
napari_yolo5_mitosis_detector/_tests/utility.py
napari_yolo5_mitosis_detector-0.0.1.dist-info/LICENSE
napari_yolo5_mitosis_detector-0.0.1.dist-info/METADATA
napari_yolo5_mitosis_detector-0.0.1.dist-info/WHEEL
napari_yolo5_mitosis_detector-0.0.1.dist-info/entry_points.txt
napari_yolo5_mitosis_detector-0.0.1.dist-info/top_level.txt
napari_yolo5_mitosis_detector-0.0.1.dist-info/RECORD
