Metadata-Version: 2.1
Name: napari-yolo5-mitosis-detector
Version: 0.0.1
Summary: A simple plugin to use yolo5 for mitosis detection with napari
Home-page: https://github.com/TPoquillon/napari-yolo5-mitosis-detector
Author: Titouan Poquillon
Author-email: titouan.poquillon@gmail.com
License: BSD-3-Clause
Project-URL: Bug Tracker, https://github.com/TPoquillon/napari-yolo5-mitosis-detector/issues
Project-URL: Documentation, https://github.com/TPoquillon/napari-yolo5-mitosis-detector#README.md
Project-URL: Source Code, https://github.com/TPoquillon/napari-yolo5-mitosis-detector
Project-URL: User Support, https://github.com/TPoquillon/napari-yolo5-mitosis-detector/issues
Classifier: Development Status :: 2 - Pre-Alpha
Classifier: Framework :: napari
Classifier: Intended Audience :: Developers
Classifier: License :: OSI Approved :: BSD License
Classifier: Operating System :: OS Independent
Classifier: Programming Language :: Python
Classifier: Programming Language :: Python :: 3
Classifier: Programming Language :: Python :: 3 :: Only
Classifier: Programming Language :: Python :: 3.8
Classifier: Programming Language :: Python :: 3.9
Classifier: Programming Language :: Python :: 3.10
Classifier: Programming Language :: Python :: 3.11
Classifier: Topic :: Scientific/Engineering :: Image Processing
Requires-Python: >=3.9
License-File: LICENSE
Requires-Dist: numpy ==1.26.2
Requires-Dist: magicgui ==0.8.0
Requires-Dist: qtpy ==2.4.1
Requires-Dist: scikit-image ==0.20.0
Requires-Dist: opencv-python ==4.8.1.78
Requires-Dist: torch ==2.1.1
Requires-Dist: ultralytics ==8.0.222
Requires-Dist: shapely ==2.0.2
Requires-Dist: importlib-resources ==6.1.1
Requires-Dist: pandas ==2.1.3
Requires-Dist: napari-aicsimageio ==0.7.2
Provides-Extra: testing
Requires-Dist: tox ; extra == 'testing'
Requires-Dist: pytest ; extra == 'testing'
Requires-Dist: pytest-cov ; extra == 'testing'
Requires-Dist: pytest-qt ; extra == 'testing'
Requires-Dist: napari ; extra == 'testing'
Requires-Dist: pyqt5 ; extra == 'testing'
